ddzl_project/dd_win32.py
ddzl_project/init.py
ddzl_project-0.3.dist-info/METADATA
ddzl_project-0.3.dist-info/WHEEL
ddzl_project-0.3.dist-info/top_level.txt
ddzl_project-0.3.dist-info/RECORD
