Metadata-Version: 2.1
Name: ddzl-project
Version: 0.3
Summary: ddzl_project
Home-page: UNKNOWN
Author: wangyu
Author-email: wangyu@ddzl.com
License: MIT
Keywords: ddzl_project
Platform: UNKNOWN
Classifier: Programming Language :: Python :: 3
Classifier: License :: OSI Approved :: MIT License
Requires-Python: >=3.6
